MANIFEST.in
README
setup.cfg
setup.py
doc/LICENSE
doc/VERSION
lib/repoze/__init__.py
lib/repoze.what.plugins.redis.egg-info/PKG-INFO
lib/repoze.what.plugins.redis.egg-info/SOURCES.txt
lib/repoze.what.plugins.redis.egg-info/dependency_links.txt
lib/repoze.what.plugins.redis.egg-info/namespace_packages.txt
lib/repoze.what.plugins.redis.egg-info/not-zip-safe
lib/repoze.what.plugins.redis.egg-info/requires.txt
lib/repoze.what.plugins.redis.egg-info/top_level.txt
lib/repoze/what/__init__.py
lib/repoze/what/plugins/__init__.py
lib/repoze/what/plugins/redis/__init__.py
lib/repoze/what/plugins/redis/adapters.py
test/.coverage
test/fixture.py
test/test_adapter.py