Metadata-Version: 1.0
Name: repoze.what.plugins.redis
Version: 1.0rc1
Summary: The repoze.what Redis plugin
Home-page: http://bitbucket.org/ares/repozewhatpluginsredis/
Author: Jonas Melian
Author-email: devel@jonasmelian.com
License: Apache License, Version 2.0
Keywords: web application server wsgi authorization redis repoze
Platform: any
Classifier: Development Status :: 4 - Beta
Classifier: Environment :: Web Environment
Classifier: Intended Audience :: Developers
Classifier: License :: OSI Approved :: Apache Software License
Classifier: Operating System :: OS Independent
Classifier: Programming Language :: Python
Classifier: Topic :: Database
Classifier: Topic :: Internet :: WWW/HTTP :: WSGI
Classifier: Topic :: Security
